pymangaj/__init__.py
pymangaj/chapmanganato.py
pymangaj/lermanga.py
pymangaj/mangalivre.py
pymangaj/muitomanga.py
pymangaj/pymangaj.py
pymangaj-0.2.0.dist-info/LICENSE
pymangaj-0.2.0.dist-info/METADATA
pymangaj-0.2.0.dist-info/WHEEL
pymangaj-0.2.0.dist-info/top_level.txt
pymangaj-0.2.0.dist-info/RECORD
