Metadata-Version: 2.1
Name: pymangaj
Version: 0.2.0
Summary: Search and download mangas.
Author-email: Jean Jacques Barros <jjean.jacques10@gmail.com>
License: MIT License
Project-URL: homepage, https://pypi.org/project/pymangaj/
Project-URL: documentation, https://github.com/jjeanjacques10/pymangaj
Project-URL: repository, https://github.com/jjeanjacques10/pymangaj
Classifier: Development Status :: 3 - Alpha
Classifier: License :: OSI Approved :: MIT License
Classifier: Programming Language :: Python :: 3
Classifier: Programming Language :: Python :: 3.6
Classifier: Programming Language :: Python :: 3.7
Classifier: Programming Language :: Python :: 3.8
Classifier: Programming Language :: Python :: 3.9
Requires-Python: >=3.6
License-File: LICENSE
Requires-Dist: requests (==2.28.1)
Requires-Dist: beautifulsoup4 (==4.12.2)
Provides-Extra: test
Requires-Dist: pytest ; extra == 'test'
